FTIRE/FT.py
FTIRE/FT3.py
FTIRE/SIR.py
FTIRE/SIR2.py
FTIRE/SpCov.py
FTIRE/__init__.py
FTIRE/ftire.py
FTIRE/genxy.py
FTIRE/dcor/__init__.py
FTIRE/dcor/_dcor.py
FTIRE/dcor/_dcor_internals.py
FTIRE/dcor/_energy.py
FTIRE/dcor/_fast_dcov_avl.py
FTIRE/dcor/_fast_dcov_mergesort.py
FTIRE/dcor/_hypothesis.py
FTIRE/dcor/_partial_dcor.py
FTIRE/dcor/_rowwise.py
FTIRE/dcor/_utils.py
FTIRE/dcor/distances.py
FTIRE/dcor/homogeneity.py
FTIRE/dcor/independence.py
FTIRE/dcor/tests/__init__.py
FTIRE/dcor/tests/test_dcor.py
FTIRE/dcor/tests/test_homogeneity.py
FTIRE/dcor/tests/test_independence.py
FTIRE/dcor/tests/test_package.py
FTIRE/dcor/tests/test_rowwise.py
ADMMFTIRE-0.0.3.dist-info/LICENSE
ADMMFTIRE-0.0.3.dist-info/METADATA
ADMMFTIRE-0.0.3.dist-info/WHEEL
ADMMFTIRE-0.0.3.dist-info/top_level.txt
ADMMFTIRE-0.0.3.dist-info/RECORD
