Metadata-Version: 2.1
Name: ADMMFTIRE
Version: 0.0.3
Summary: An ADMMFTIRE package
Home-page: https://github.com/SDR-VariableSelection/ADMMFTIRE
Author: Jiaying Weng
Author-email: jweng@bentley.edu
License: UNKNOWN
Platform: UNKNOWN
Classifier: Programming Language :: Python :: 3
Classifier: License :: OSI Approved :: MIT License
Classifier: Operating System :: OS Independent
Requires-Python: >=3.6
